main.py
minipangram-0.1.0.dist-info/METADATA
minipangram-0.1.0.dist-info/WHEEL
minipangram-0.1.0.dist-info/top_level.txt
minipangram-0.1.0.dist-info/RECORD
