Metadata-Version: 2.4
Name: minipangram
Version: 0.1.0
Summary: A Python package for working with pangrams
Author-email: Rémi Louf <remilouf@protonmail.com>
Classifier: Development Status :: 3 - Alpha
Classifier: Intended Audience :: Developers
Classifier: Programming Language :: Python :: 3
Classifier: Programming Language :: Python :: 3.11
Requires-Python: >=3.11
